.gitignore
MANIFEST.in
README.rst
bootstrap.py
buildout.cfg
setup.py
docs/HISTORY.txt
src/collective/__init__.py
src/collective.funkload.egg-info/PKG-INFO
src/collective.funkload.egg-info/SOURCES.txt
src/collective.funkload.egg-info/dependency_links.txt
src/collective.funkload.egg-info/entry_points.txt
src/collective.funkload.egg-info/namespace_packages.txt
src/collective.funkload.egg-info/not-zip-safe
src/collective.funkload.egg-info/requires.txt
src/collective.funkload.egg-info/top_level.txt
src/collective/funkload/__init__.py
src/collective/funkload/bench.py
src/collective/funkload/continuous.txt
src/collective/funkload/diff.py
src/collective/funkload/label.pt
src/collective/funkload/label.py
src/collective/funkload/labels.txt
src/collective/funkload/loop.py
src/collective/funkload/recorder.py
src/collective/funkload/report.py
src/collective/funkload/stamp.py
src/collective/funkload/testcase.py
src/collective/funkload/testing.py
src/collective/funkload/data/ScriptTestCase.tpl
src/collective/funkload/tests/__init__.py
src/collective/funkload/tests/bench.xml
src/collective/funkload/tests/tests.py
src/collective/funkload/tests/src/foo/FooTestCase.conf
src/collective/funkload/tests/src/foo/__init__.py
src/collective/funkload/tests/src/foo/sampletests.py