Metadata-Version: 1.1
Name: collective.funkload
Version: 0.4
Summary: Zope and Plone focussed extensions to funkload
Home-page: https://github.com/collective/collective.funkload
Author: Ross Patterson
Author-email: me@rpatterson.net
License: GPL
Platform: UNKNOWN
Classifier: Programming Language :: Python
Classifier: Topic :: Software Development :: Libraries :: Python Modules
